tictax/__init__.py
tictax/cli.py
tictax/tictax.py
tictax/tests/test.fa
tictax-0.1.3.dist-info/METADATA
tictax-0.1.3.dist-info/RECORD
tictax-0.1.3.dist-info/WHEEL
tictax-0.1.3.dist-info/entry_points.txt
tictax-0.1.3.dist-info/top_level.txt
tictax-0.1.3.dist-info/zip-safe
