Metadata-Version: 2.1
Name: tictax
Version: 0.1.3
Summary: Streaming nucleotide sequence classification with web services
Home-page: https://github.com/bede/tictax
Author: Bede Constantinides
Author-email: bedeabc@gmail.com
License: GPL
Platform: UNKNOWN
Classifier: Development Status :: 3 - Alpha
Classifier: Topic :: Scientific/Engineering :: Bio-Informatics
Classifier: License :: OSI Approved :: GNU General Public License v3 (GPLv3)
Classifier: Programming Language :: Python :: 3
Classifier: Programming Language :: Python :: 3.5
Classifier: Programming Language :: Python :: 3.6
Requires-Dist: argh (==0.26.2)
Requires-Dist: tqdm (==4.24.0)
Requires-Dist: aiohttp (==2.3.7)
Requires-Dist: biopython (==1.72)
